generalized_elastic_net/__init__.py
generalized_elastic_net/generalized_elastic_net.py
generalized_elastic_net/version.py
test/__init__.py
test/test_solver.py
generalized_elastic_net-1.0.1.dist-info/LICENSE
generalized_elastic_net-1.0.1.dist-info/METADATA
generalized_elastic_net-1.0.1.dist-info/WHEEL
generalized_elastic_net-1.0.1.dist-info/top_level.txt
generalized_elastic_net-1.0.1.dist-info/RECORD
