Metadata-Version: 2.1
Name: generalized-elastic-net
Version: 1.0.1
Summary: Generalized Elastic Net
Home-page: https://github.com/yujiading/generalized-elastic-net
Author: Yujia Ding
Author-email: dingyujia2013@gmail.com
License: UNKNOWN
Platform: UNKNOWN
Classifier: Programming Language :: Python :: 3
Classifier: License :: OSI Approved :: MIT License
Classifier: Operating System :: OS Independent
Requires-Python: >=3.5
